README.md
setup.py
efunx/__init__.py
efunx/__main__.py
efunx/efunx.py
efunx/get.py
efunx/registry.py
efunx.egg-info/PKG-INFO
efunx.egg-info/SOURCES.txt
efunx.egg-info/dependency_links.txt
efunx.egg-info/entry_points.txt
efunx.egg-info/not-zip-safe
efunx.egg-info/requires.txt
efunx.egg-info/top_level.txt